deployer_scripts/__init__.py
deployer_scripts/analyze_volumes.py
deployer_scripts/config_utils.py
deployer_scripts/detect_framework.py
deployer_scripts/detect_project.py
deployer_scripts/pack_project.py
deployer_scripts/standalone_config.py
deployer_scripts/upload_to_server.py
deployer_scripts-1.0.0.dist-info/METADATA
deployer_scripts-1.0.0.dist-info/WHEEL
deployer_scripts-1.0.0.dist-info/entry_points.txt
deployer_scripts-1.0.0.dist-info/RECORD
